{
  "owner": "dmdorta1111",
  "slug": "nima-core",
  "displayName": "NIMA Core",
  "latest": {
    "version": "1.1.3",
    "publishedAt": 1770672761613,
    "commit": null
  },
  "history": [
    {
      "version": "1.0.1",
      "publishedAt": 1770519020241,
      "commit": "https://github.com/openclaw/skills/commit/04ac6b51cc35469a308eea76136e2ea89f69f9c0"
    },
    {
      "version": "1.0.0",
      "publishedAt": 1770450849405,
      "commit": "https://github.com/openclaw/skills/commit/82820a2650a491916128db5b3cbb354cc54aacfe"
    }
  ]
}
